[
  {
    "file": "D:\\Development\\PY\\CLI\\parse-master-cli\\data\\ingested\\647249ff47d5ffb9ec1bb2b2d60cfb2a_6a81441f.txt",
    "match_type": [
      "text"
    ],
    "matches": [
      {
        "key": "text",
        "text": "<!DOCTYPE html PUBLIC \"-//W3C//DTD XHTML 1.0 Transitional//EN\" \"http://www.w3.org/TR/xhtml1/DTD/xhtml1-transitional.dtd\">",
        "line": 4
      }
    ]
  },
  {
    "file": "D:\\Development\\PY\\CLI\\parse-master-cli\\data\\ingested\\ed8b701f8011ee3029358d6a4b1fc7e7_45973d1d.txt",
    "match_type": [
      "text"
    ],
    "matches": [
      {
        "key": "text",
        "text": "<!DOCTYPE html PUBLIC \"-//W3C//DTD XHTML 1.0 Transitional//EN\" \"http://www.w3.org/TR/xhtml1/DTD/xhtml1-transitional.dtd\">",
        "line": 4
      }
    ]
  }
]